{
  "summary": {
    "profileCount": 39,
    "websiteVerifiedCount": 30,
    "websiteMissingCount": 9,
    "websiteFailedCount": 0,
    "contactUrlCount": 26,
    "contactVerifiedCount": 26,
    "linkedinUrlCount": 15,
    "newsLinkCount": 7,
    "newsLinkVerifiedCount": 7,
    "qaStatusCounts": {
      "unresolved": 9,
      "verified_with_gaps": 30
    }
  },
  "metadata": {
    "title": "Company Website Probe",
    "generatedAt": "2026-07-15T19:07:48.341709+00:00",
    "profileCount": 39,
    "methodNotes": [
      "This validates public website, contact, source, and news-link availability and finds likely cultivar/variety evidence links.",
      "Keyword counts are page-level hints, not cultivar counts.",
      "LinkedIn URLs are syntax-checked only because LinkedIn often blocks automated checks; manual browser QA is still required."
    ]
  },
  "companies": [
    {
      "canonicalName": "Bloom Fresh International",
      "website": "https://www.bloomfresh.com/",
      "ok": true,
      "status": 200,
      "finalUrl": "https://bloomfresh.com/",
      "error": "",
      "title": "BloomFresh.com",
      "keywordCounts": {
        "variety": 1,
        "brand": 2,
        "apple": 5
      },
      "evidenceLinks": [],
      "contact": {
        "url": "",
        "ok": false,
        "status": "",
        "finalUrl": "",
        "error": "No URL",
        "title": "",
        "checkType": "missing"
      },
      "source": {
        "url": "https://www.bloomfresh.com/",
        "ok": true,
        "status": 200,
        "finalUrl": "https://bloomfresh.com/",
        "error": "",
        "title": "BloomFresh.com",
        "checkType": "same_as_website"
      },
      "linkedin": {
        "url": "https://www.linkedin.com/company/bloomfresh-global/",
        "ok": true,
        "status": "not fetched",
        "finalUrl": "https://www.linkedin.com/company/bloomfresh-global/",
        "error": "LinkedIn blocks many automated checks; manual browser QA required.",
        "title": "",
        "checkType": "linkedin_url_format"
      },
      "news": [],
      "qaStatus": "verified_with_gaps",
      "auditFlags": [
        "missing_contact_url",
        "linkedin_manual_check_required"
      ],
      "probedAt": "2026-07-15T19:06:43.405889+00:00"
    },
    {
      "canonicalName": "Sun World International",
      "website": "https://www.sun-world.com/",
      "ok": true,
      "status": 200,
      "finalUrl": "https://www.sun-world.com/",
      "error": "",
      "title": "Sun World - Global Fruit Variety Development &amp; Licensing",
      "keywordCounts": {
        "variety": 17,
        "varieties": 4,
        "genetic": 5,
        "genetics": 5,
        "brand": 36,
        "grape": 46,
        "cherry": 1
      },
      "evidenceLinks": [
        {
          "label": "Variety Rights Management",
          "url": "https://www.sun-world.com/variety-rights-management"
        },
        {
          "label": "Branding",
          "url": "https://www.sun-world.com/branding"
        },
        {
          "label": "Our Products",
          "url": "https://www.sun-world.com/brands"
        },
        {
          "label": "Mangoes",
          "url": "https://www.sun-world.com/brands-mangoes"
        },
        {
          "label": "Stone Fruit",
          "url": "https://www.sun-world.com/brands-stone-fruit"
        },
        {
          "label": "FIND OUT MORE",
          "url": "https://www.sun-world.com/variety-rights-management?hsLang=en"
        },
        {
          "label": "SEE MORE",
          "url": "https://www.sun-world.com/branding?hsLang=en"
        }
      ],
      "contact": {
        "url": "https://www.sun-world.com/contact-us",
        "ok": true,
        "status": 200,
        "finalUrl": "https://www.sun-world.com/contact-us",
        "error": "",
        "title": "CONTACT US",
        "checkType": "http"
      },
      "source": {
        "url": "https://www.sun-world.com/",
        "ok": true,
        "status": 200,
        "finalUrl": "https://www.sun-world.com/",
        "error": "",
        "title": "Sun World - Global Fruit Variety Development &amp; Licensing",
        "checkType": "same_as_website"
      },
      "linkedin": {
        "url": "",
        "ok": false,
        "status": "",
        "finalUrl": "",
        "error": "No URL",
        "title": "",
        "checkType": "missing"
      },
      "news": [],
      "qaStatus": "verified_with_gaps",
      "auditFlags": [
        "missing_linkedin_url"
      ],
      "probedAt": "2026-07-15T19:06:45.178105+00:00"
    },
    {
      "canonicalName": "International Fruit Genetics",
      "website": "https://www.bloomfresh.com/",
      "ok": true,
      "status": 200,
      "finalUrl": "https://bloomfresh.com/",
      "error": "",
      "title": "BloomFresh.com",
      "keywordCounts": {
        "variety": 1,
        "brand": 2,
        "apple": 5
      },
      "evidenceLinks": [],
      "contact": {
        "url": "",
        "ok": false,
        "status": "",
        "finalUrl": "",
        "error": "No URL",
        "title": "",
        "checkType": "missing"
      },
      "source": {
        "url": "https://www.bloomfresh.com/",
        "ok": true,
        "status": 200,
        "finalUrl": "https://bloomfresh.com/",
        "error": "",
        "title": "BloomFresh.com",
        "checkType": "same_as_website"
      },
      "linkedin": {
        "url": "https://www.linkedin.com/company/bloomfresh-global/",
        "ok": true,
        "status": "not fetched",
        "finalUrl": "https://www.linkedin.com/company/bloomfresh-global/",
        "error": "LinkedIn blocks many automated checks; manual browser QA required.",
        "title": "",
        "checkType": "linkedin_url_format"
      },
      "news": [],
      "qaStatus": "verified_with_gaps",
      "auditFlags": [
        "missing_contact_url",
        "linkedin_manual_check_required"
      ],
      "probedAt": "2026-07-15T19:06:45.708670+00:00"
    },
    {
      "canonicalName": "SNFL Group",
      "website": "https://snflgroup.com/",
      "ok": true,
      "status": 200,
      "finalUrl": "https://snflgroup.com/",
      "error": "",
      "title": "Grape Innovation For Healthier Future | Table Grapes",
      "keywordCounts": {
        "varieties": 113,
        "genetic": 3,
        "genetics": 3,
        "grape": 19,
        "apple": 1
      },
      "evidenceLinks": [
        {
          "label": "Varieties",
          "url": "https://snflgroup.com/varieties/"
        },
        {
          "label": "Red Seedless",
          "url": "https://snflgroup.com/varieties_category/red-seedless/"
        },
        {
          "label": "Green Seedless",
          "url": "https://snflgroup.com/varieties_category/green-seedless/"
        },
        {
          "label": "Black Seedless",
          "url": "https://snflgroup.com/varieties_category/black-seedless/"
        },
        {
          "label": "Seedless Specialty",
          "url": "https://snflgroup.com/varieties_category/seedless-specialty/"
        },
        {
          "label": "",
          "url": "https://www.facebook.com/snflsheehangrapes/"
        },
        {
          "label": "",
          "url": "https://www.instagram.com/snfl_sheehan_grapes/?hl=en"
        },
        {
          "label": "",
          "url": "https://www.linkedin.com/company/sheehan-genetics/?viewAsMember=true"
        }
      ],
      "contact": {
        "url": "https://snflgroup.com/contact/",
        "ok": true,
        "status": 200,
        "finalUrl": "https://snflgroup.com/contact/",
        "error": "",
        "title": "Contact SNFL Experts for Technical and Commercial Assessment",
        "checkType": "http"
      },
      "source": {
        "url": "https://snflgroup.com/",
        "ok": true,
        "status": 200,
        "finalUrl": "https://snflgroup.com/",
        "error": "",
        "title": "Grape Innovation For Healthier Future | Table Grapes",
        "checkType": "same_as_website"
      },
      "linkedin": {
        "url": "https://www.linkedin.com/company/special-new-fruit-licensing-limited/",
        "ok": true,
        "status": "not fetched",
        "finalUrl": "https://www.linkedin.com/company/special-new-fruit-licensing-limited/",
        "error": "LinkedIn blocks many automated checks; manual browser QA required.",
        "title": "",
        "checkType": "linkedin_url_format"
      },
      "news": [],
      "qaStatus": "verified_with_gaps",
      "auditFlags": [
        "linkedin_manual_check_required"
      ],
      "probedAt": "2026-07-15T19:06:47.150279+00:00"
    },
    {
      "canonicalName": "Driscoll's",
      "website": "https://www.driscolls.com/",
      "ok": true,
      "status": 200,
      "finalUrl": "https://www.driscolls.com/",
      "error": "",
      "title": "Driscoll&#x27;s",
      "keywordCounts": {
        "blueberry": 2,
        "strawberry": 46,
        "raspberry": 2,
        "blackberry": 3
      },
      "evidenceLinks": [],
      "contact": {
        "url": "https://www.driscolls.com/about/contact-us",
        "ok": true,
        "status": 200,
        "finalUrl": "https://www.driscolls.com/about/contact-us",
        "error": "",
        "title": "Contact Us",
        "checkType": "http"
      },
      "source": {
        "url": "https://www.driscolls.com/",
        "ok": true,
        "status": 200,
        "finalUrl": "https://www.driscolls.com/",
        "error": "",
        "title": "Driscoll&#x27;s",
        "checkType": "same_as_website"
      },
      "linkedin": {
        "url": "https://www.linkedin.com/company/driscoll's/",
        "ok": true,
        "status": "not fetched",
        "finalUrl": "https://www.linkedin.com/company/driscoll's/",
        "error": "LinkedIn blocks many automated checks; manual browser QA required.",
        "title": "",
        "checkType": "linkedin_url_format"
      },
      "news": [],
      "qaStatus": "verified_with_gaps",
      "auditFlags": [
        "linkedin_manual_check_required"
      ],
      "probedAt": "2026-07-15T19:06:48.082838+00:00"
    },
    {
      "canonicalName": "BerryWorld Plus",
      "website": "https://www.berryworld.com/",
      "ok": true,
      "status": 200,
      "finalUrl": "https://www.berryworld.com/",
      "error": "",
      "title": "Award-winning fresh berries | BerryWorld",
      "keywordCounts": {
        "varieties": 2,
        "brand": 145,
        "blueberry": 5,
        "strawberry": 5,
        "raspberry": 5,
        "blackberry": 5,
        "apple": 2
      },
      "evidenceLinks": [
        {
          "label": "Varieties",
          "url": "https://www.berryworld.com/berries/varieties"
        }
      ],
      "contact": {
        "url": "https://www.berryworld.com/contact",
        "ok": true,
        "status": 200,
        "finalUrl": "https://www.berryworld.com/contact",
        "error": "",
        "title": "Let&#039;s talk berries | BerryWorld",
        "checkType": "http"
      },
      "source": {
        "url": "https://www.berryworld.com/",
        "ok": true,
        "status": 200,
        "finalUrl": "https://www.berryworld.com/",
        "error": "",
        "title": "Award-winning fresh berries | BerryWorld",
        "checkType": "same_as_website"
      },
      "linkedin": {
        "url": "https://www.linkedin.com/company/berryworld/",
        "ok": true,
        "status": "not fetched",
        "finalUrl": "https://www.linkedin.com/company/berryworld/",
        "error": "LinkedIn blocks many automated checks; manual browser QA required.",
        "title": "",
        "checkType": "linkedin_url_format"
      },
      "news": [],
      "qaStatus": "verified_with_gaps",
      "auditFlags": [
        "linkedin_manual_check_required"
      ],
      "probedAt": "2026-07-15T19:06:49.899542+00:00"
    },
    {
      "canonicalName": "Fall Creek Farm & Nursery",
      "website": "https://www.fallcreeknursery.com/",
      "ok": true,
      "status": 200,
      "finalUrl": "https://www.fallcreeknursery.com/",
      "error": "",
      "title": "Fall Creek® | World's Leading Blueberry Nursery Stock Company",
      "keywordCounts": {
        "variety": 20,
        "varieties": 26,
        "genetic": 5,
        "genetics": 5,
        "brand": 2,
        "blueberry": 19
      },
      "evidenceLinks": [
        {
          "label": "Nursery Varieties",
          "url": "https://www.fallcreeknursery.com/nurseries/varieties"
        },
        {
          "label": "Blueberry Varieties",
          "url": "https://www.fallcreeknursery.com/commercial-fruit-growers/varieties"
        },
        {
          "label": "Variety Innovations",
          "url": "https://www.fallcreeknursery.com/variety-innovations"
        },
        {
          "label": "Overview",
          "url": "https://www.fallcreeknursery.com/variety-innovations/overview"
        },
        {
          "label": "Fall Creek® Breeding",
          "url": "https://www.fallcreeknursery.com/variety-innovations/fall-creek-breeding"
        },
        {
          "label": "The Future of Blueberries",
          "url": "https://www.fallcreeknursery.com/variety-innovations/the-future-of-blueberries"
        },
        {
          "label": "New Varieties",
          "url": "https://www.fallcreeknursery.com/variety-innovations/new-varieties"
        },
        {
          "label": "Fall Creek® Collection",
          "url": "https://www.fallcreeknursery.com/variety-innovations/fall-creek-collection"
        },
        {
          "label": "Contact Us",
          "url": "https://www.fallcreeknursery.com/commercial-fruit-growers/varieties/inquire"
        }
      ],
      "contact": {
        "url": "https://www.fallcreeknursery.com/contact-us",
        "ok": true,
        "status": 200,
        "finalUrl": "https://www.fallcreeknursery.com/contact-us",
        "error": "",
        "title": "Plant Preview Program | Fall Creek®",
        "checkType": "http"
      },
      "source": {
        "url": "https://www.fallcreeknursery.com/",
        "ok": true,
        "status": 200,
        "finalUrl": "https://www.fallcreeknursery.com/",
        "error": "",
        "title": "Fall Creek® | World's Leading Blueberry Nursery Stock Company",
        "checkType": "same_as_website"
      },
      "linkedin": {
        "url": "",
        "ok": false,
        "status": "",
        "finalUrl": "",
        "error": "No URL",
        "title": "",
        "checkType": "missing"
      },
      "news": [
        {
          "url": "https://www.fallcreeknursery.com/news",
          "ok": true,
          "status": 200,
          "finalUrl": "https://www.fallcreeknursery.com/news",
          "error": "",
          "title": "Plant Preview Program | Fall Creek®",
          "checkType": "http",
          "label": "Fall Creek news"
        }
      ],
      "qaStatus": "verified_with_gaps",
      "auditFlags": [
        "missing_linkedin_url"
      ],
      "probedAt": "2026-07-15T19:06:53.963220+00:00"
    },
    {
      "canonicalName": "Zaiger's Genetics",
      "website": "https://www.davewilson.com/about/zaiger/",
      "ok": true,
      "status": 200,
      "finalUrl": "https://www.davewilson.com/about/zaiger/",
      "error": "",
      "title": "Zaiger Genetics | Dave Wilson Nursery",
      "keywordCounts": {
        "variety": 4,
        "genetic": 12,
        "genetics": 12,
        "patent": 2,
        "trademark": 2,
        "apple": 3
      },
      "evidenceLinks": [],
      "contact": {
        "url": "https://www.davewilson.com/contact/",
        "ok": true,
        "status": 200,
        "finalUrl": "https://www.davewilson.com/contact/",
        "error": "",
        "title": "Contact | Dave Wilson Nursery",
        "checkType": "http"
      },
      "source": {
        "url": "https://www.davewilson.com/about/zaiger/",
        "ok": true,
        "status": 200,
        "finalUrl": "https://www.davewilson.com/about/zaiger/",
        "error": "",
        "title": "Zaiger Genetics | Dave Wilson Nursery",
        "checkType": "same_as_website"
      },
      "linkedin": {
        "url": "",
        "ok": false,
        "status": "",
        "finalUrl": "",
        "error": "No URL",
        "title": "",
        "checkType": "missing"
      },
      "news": [],
      "qaStatus": "verified_with_gaps",
      "auditFlags": [
        "missing_linkedin_url"
      ],
      "probedAt": "2026-07-15T19:06:54.388244+00:00"
    },
    {
      "canonicalName": "Agro Selections Fruits S.A.S.",
      "website": "",
      "ok": false,
      "status": "",
      "finalUrl": "",
      "error": "No URL",
      "title": "",
      "keywordCounts": {},
      "evidenceLinks": [],
      "contact": {
        "url": "",
        "ok": false,
        "status": "",
        "finalUrl": "",
        "error": "No URL",
        "title": "",
        "checkType": "missing"
      },
      "source": {
        "url": "",
        "ok": false,
        "status": "",
        "finalUrl": "",
        "error": "No URL",
        "title": "",
        "checkType": "missing"
      },
      "linkedin": {
        "url": "",
        "ok": false,
        "status": "",
        "finalUrl": "",
        "error": "No URL",
        "title": "",
        "checkType": "missing"
      },
      "news": [],
      "qaStatus": "unresolved",
      "auditFlags": [
        "missing_website",
        "missing_contact_url",
        "missing_linkedin_url",
        "missing_source_url"
      ],
      "probedAt": "2026-07-15T19:06:54.388244+00:00"
    },
    {
      "canonicalName": "Berry Genetics",
      "website": "",
      "ok": false,
      "status": "",
      "finalUrl": "",
      "error": "No URL",
      "title": "",
      "keywordCounts": {},
      "evidenceLinks": [],
      "contact": {
        "url": "",
        "ok": false,
        "status": "",
        "finalUrl": "",
        "error": "No URL",
        "title": "",
        "checkType": "missing"
      },
      "source": {
        "url": "",
        "ok": false,
        "status": "",
        "finalUrl": "",
        "error": "No URL",
        "title": "",
        "checkType": "missing"
      },
      "linkedin": {
        "url": "",
        "ok": false,
        "status": "",
        "finalUrl": "",
        "error": "No URL",
        "title": "",
        "checkType": "missing"
      },
      "news": [],
      "qaStatus": "unresolved",
      "auditFlags": [
        "missing_website",
        "missing_contact_url",
        "missing_linkedin_url",
        "missing_source_url"
      ],
      "probedAt": "2026-07-15T19:06:54.388244+00:00"
    },
    {
      "canonicalName": "Cerasina GmbH",
      "website": "https://cerasina.com/",
      "ok": true,
      "status": 200,
      "finalUrl": "https://cerasina.com/",
      "error": "",
      "title": "Obstbau Stoppel - Süsskirschensorten und Kirschenzucht im frühen und späten Reifebereich | Süsskirschensorten und Kirschenzucht für den frühen und späten Reifebereich sowie Kirschunterlagen und Erdbeeren",
      "keywordCounts": {
        "brand": 6,
        "apple": 2
      },
      "evidenceLinks": [],
      "contact": {
        "url": "https://cerasina.com/kontakt/",
        "ok": true,
        "status": 200,
        "finalUrl": "https://cerasina.com/kontakt/",
        "error": "",
        "title": "Kontakt | Obstbau Stoppel - Süsskirschensorten und Kirschenzucht im frühen und späten Reifebereich",
        "checkType": "http"
      },
      "source": {
        "url": "https://cerasina.com/",
        "ok": true,
        "status": 200,
        "finalUrl": "https://cerasina.com/",
        "error": "",
        "title": "Obstbau Stoppel - Süsskirschensorten und Kirschenzucht im frühen und späten Reifebereich | Süsskirschensorten und Kirschenzucht für den frühen und späten Reifebereich sowie Kirschunterlagen und Erdbeeren",
        "checkType": "same_as_website"
      },
      "linkedin": {
        "url": "",
        "ok": false,
        "status": "",
        "finalUrl": "",
        "error": "No URL",
        "title": "",
        "checkType": "missing"
      },
      "news": [],
      "qaStatus": "verified_with_gaps",
      "auditFlags": [
        "missing_linkedin_url"
      ],
      "probedAt": "2026-07-15T19:06:59.714257+00:00"
    },
    {
      "canonicalName": "B Q Genetics",
      "website": "",
      "ok": false,
      "status": "",
      "finalUrl": "",
      "error": "No URL",
      "title": "",
      "keywordCounts": {},
      "evidenceLinks": [],
      "contact": {
        "url": "",
        "ok": false,
        "status": "",
        "finalUrl": "",
        "error": "No URL",
        "title": "",
        "checkType": "missing"
      },
      "source": {
        "url": "",
        "ok": false,
        "status": "",
        "finalUrl": "",
        "error": "No URL",
        "title": "",
        "checkType": "missing"
      },
      "linkedin": {
        "url": "",
        "ok": false,
        "status": "",
        "finalUrl": "",
        "error": "No URL",
        "title": "",
        "checkType": "missing"
      },
      "news": [],
      "qaStatus": "unresolved",
      "auditFlags": [
        "missing_website",
        "missing_contact_url",
        "missing_linkedin_url",
        "missing_source_url"
      ],
      "probedAt": "2026-07-15T19:06:59.714257+00:00"
    },
    {
      "canonicalName": "Berry Blue",
      "website": "",
      "ok": false,
      "status": "",
      "finalUrl": "",
      "error": "No URL",
      "title": "",
      "keywordCounts": {},
      "evidenceLinks": [],
      "contact": {
        "url": "",
        "ok": false,
        "status": "",
        "finalUrl": "",
        "error": "No URL",
        "title": "",
        "checkType": "missing"
      },
      "source": {
        "url": "",
        "ok": false,
        "status": "",
        "finalUrl": "",
        "error": "No URL",
        "title": "",
        "checkType": "missing"
      },
      "linkedin": {
        "url": "",
        "ok": false,
        "status": "",
        "finalUrl": "",
        "error": "No URL",
        "title": "",
        "checkType": "missing"
      },
      "news": [],
      "qaStatus": "unresolved",
      "auditFlags": [
        "missing_website",
        "missing_contact_url",
        "missing_linkedin_url",
        "missing_source_url"
      ],
      "probedAt": "2026-07-15T19:06:59.714257+00:00"
    },
    {
      "canonicalName": "Allberry B.V.",
      "website": "",
      "ok": false,
      "status": "",
      "finalUrl": "",
      "error": "No URL",
      "title": "",
      "keywordCounts": {},
      "evidenceLinks": [],
      "contact": {
        "url": "",
        "ok": false,
        "status": "",
        "finalUrl": "",
        "error": "No URL",
        "title": "",
        "checkType": "missing"
      },
      "source": {
        "url": "",
        "ok": false,
        "status": "",
        "finalUrl": "",
        "error": "No URL",
        "title": "",
        "checkType": "missing"
      },
      "linkedin": {
        "url": "",
        "ok": false,
        "status": "",
        "finalUrl": "",
        "error": "No URL",
        "title": "",
        "checkType": "missing"
      },
      "news": [],
      "qaStatus": "unresolved",
      "auditFlags": [
        "missing_website",
        "missing_contact_url",
        "missing_linkedin_url",
        "missing_source_url"
      ],
      "probedAt": "2026-07-15T19:06:59.714257+00:00"
    },
    {
      "canonicalName": "Fruit Vision",
      "website": "",
      "ok": false,
      "status": "",
      "finalUrl": "",
      "error": "No URL",
      "title": "",
      "keywordCounts": {},
      "evidenceLinks": [],
      "contact": {
        "url": "",
        "ok": false,
        "status": "",
        "finalUrl": "",
        "error": "No URL",
        "title": "",
        "checkType": "missing"
      },
      "source": {
        "url": "",
        "ok": false,
        "status": "",
        "finalUrl": "",
        "error": "No URL",
        "title": "",
        "checkType": "missing"
      },
      "linkedin": {
        "url": "",
        "ok": false,
        "status": "",
        "finalUrl": "",
        "error": "No URL",
        "title": "",
        "checkType": "missing"
      },
      "news": [],
      "qaStatus": "unresolved",
      "auditFlags": [
        "missing_website",
        "missing_contact_url",
        "missing_linkedin_url",
        "missing_source_url"
      ],
      "probedAt": "2026-07-15T19:06:59.714257+00:00"
    },
    {
      "canonicalName": "Threefold Holdings Group",
      "website": "",
      "ok": false,
      "status": "",
      "finalUrl": "",
      "error": "No URL",
      "title": "",
      "keywordCounts": {},
      "evidenceLinks": [],
      "contact": {
        "url": "",
        "ok": false,
        "status": "",
        "finalUrl": "",
        "error": "No URL",
        "title": "",
        "checkType": "missing"
      },
      "source": {
        "url": "",
        "ok": false,
        "status": "",
        "finalUrl": "",
        "error": "No URL",
        "title": "",
        "checkType": "missing"
      },
      "linkedin": {
        "url": "",
        "ok": false,
        "status": "",
        "finalUrl": "",
        "error": "No URL",
        "title": "",
        "checkType": "missing"
      },
      "news": [],
      "qaStatus": "unresolved",
      "auditFlags": [
        "missing_website",
        "missing_contact_url",
        "missing_linkedin_url",
        "missing_source_url"
      ],
      "probedAt": "2026-07-15T19:06:59.714257+00:00"
    },
    {
      "canonicalName": "PSB Producción Vegetal S.L.",
      "website": "https://psbproduccionvegetal.com/",
      "ok": true,
      "status": 200,
      "finalUrl": "https://psbproduccionvegetal.com/",
      "error": "",
      "title": "Distribuidor de variedades de fruta de hueso: obtentores",
      "keywordCounts": {
        "patent": 4,
        "apple": 3
      },
      "evidenceLinks": [],
      "contact": {
        "url": "https://psbproduccionvegetal.com/#contacto",
        "ok": true,
        "status": 200,
        "finalUrl": "https://psbproduccionvegetal.com/#contacto",
        "error": "",
        "title": "Distribuidor de variedades de fruta de hueso: obtentores",
        "checkType": "http"
      },
      "source": {
        "url": "https://psbproduccionvegetal.com/",
        "ok": true,
        "status": 200,
        "finalUrl": "https://psbproduccionvegetal.com/",
        "error": "",
        "title": "Distribuidor de variedades de fruta de hueso: obtentores",
        "checkType": "same_as_website"
      },
      "linkedin": {
        "url": "",
        "ok": false,
        "status": "",
        "finalUrl": "",
        "error": "No URL",
        "title": "",
        "checkType": "missing"
      },
      "news": [
        {
          "url": "https://psbproduccionvegetal.com/noticias/",
          "ok": true,
          "status": 200,
          "finalUrl": "https://psbproduccionvegetal.com/noticias/",
          "error": "",
          "title": "Noticias sobre fruta de hueso, variedades y eventos",
          "checkType": "http",
          "label": "PSB news"
        }
      ],
      "qaStatus": "verified_with_gaps",
      "auditFlags": [
        "missing_linkedin_url"
      ],
      "probedAt": "2026-07-15T19:07:04.329109+00:00"
    },
    {
      "canonicalName": "S.A. Viveros Provedo",
      "website": "https://www.provedo.com/en/",
      "ok": true,
      "status": 200,
      "finalUrl": "https://www.provedo.com/en/",
      "error": "",
      "title": "Provedo - Nursery of vine plants and fruit trees | Stone Fruit Breeders",
      "keywordCounts": {
        "variety": 1,
        "varieties": 1,
        "genetic": 3,
        "brand": 8
      },
      "evidenceLinks": [],
      "contact": {
        "url": "https://www.provedo.com/en/contact/",
        "ok": true,
        "status": 200,
        "finalUrl": "https://www.provedo.com/en/contact/",
        "error": "",
        "title": "Contact Us - Viveros Provedo",
        "checkType": "http"
      },
      "source": {
        "url": "https://www.provedo.com/",
        "ok": true,
        "status": 200,
        "finalUrl": "https://www.provedo.com/en/",
        "error": "",
        "title": "Provedo - Nursery of vine plants and fruit trees | Stone Fruit Breeders",
        "checkType": "http"
      },
      "linkedin": {
        "url": "",
        "ok": false,
        "status": "",
        "finalUrl": "",
        "error": "No URL",
        "title": "",
        "checkType": "missing"
      },
      "news": [],
      "qaStatus": "verified_with_gaps",
      "auditFlags": [
        "missing_linkedin_url"
      ],
      "probedAt": "2026-07-15T19:07:07.445507+00:00"
    },
    {
      "canonicalName": "Flevo Berry Holding B.V.",
      "website": "https://flevoberry.nl/",
      "ok": true,
      "status": 200,
      "finalUrl": "https://flevoberry.nl/",
      "error": "",
      "title": "Home - en - Flevo Berry",
      "keywordCounts": {
        "variety": 1,
        "varieties": 12,
        "brand": 2,
        "strawberry": 4,
        "apple": 2
      },
      "evidenceLinks": [
        {
          "label": "Varieties",
          "url": "https://flevoberry.nl/varieties/"
        }
      ],
      "contact": {
        "url": "https://flevoberry.nl/about-us/",
        "ok": true,
        "status": 200,
        "finalUrl": "https://flevoberry.nl/about-us/",
        "error": "",
        "title": "About us - Flevo Berry",
        "checkType": "http"
      },
      "source": {
        "url": "https://flevoberry.nl/",
        "ok": true,
        "status": 200,
        "finalUrl": "https://flevoberry.nl/",
        "error": "",
        "title": "Home - en - Flevo Berry",
        "checkType": "same_as_website"
      },
      "linkedin": {
        "url": "",
        "ok": false,
        "status": "",
        "finalUrl": "",
        "error": "No URL",
        "title": "",
        "checkType": "missing"
      },
      "news": [],
      "qaStatus": "verified_with_gaps",
      "auditFlags": [
        "missing_linkedin_url"
      ],
      "probedAt": "2026-07-15T19:07:09.815312+00:00"
    },
    {
      "canonicalName": "Darbonne Pépinière S.A.S.",
      "website": "",
      "ok": false,
      "status": "",
      "finalUrl": "",
      "error": "No URL",
      "title": "",
      "keywordCounts": {},
      "evidenceLinks": [],
      "contact": {
        "url": "",
        "ok": false,
        "status": "",
        "finalUrl": "",
        "error": "No URL",
        "title": "",
        "checkType": "missing"
      },
      "source": {
        "url": "",
        "ok": false,
        "status": "",
        "finalUrl": "",
        "error": "No URL",
        "title": "",
        "checkType": "missing"
      },
      "linkedin": {
        "url": "",
        "ok": false,
        "status": "",
        "finalUrl": "",
        "error": "No URL",
        "title": "",
        "checkType": "missing"
      },
      "news": [],
      "qaStatus": "unresolved",
      "auditFlags": [
        "missing_website",
        "missing_contact_url",
        "missing_linkedin_url",
        "missing_source_url"
      ],
      "probedAt": "2026-07-15T19:07:09.815312+00:00"
    },
    {
      "canonicalName": "The Burchell Nursery",
      "website": "https://www.burchellnursery.com/",
      "ok": true,
      "status": 200,
      "finalUrl": "https://www.burchellnursery.com/",
      "error": "",
      "title": "Burchell Nursery - Wholesale Tree Nursery (Bare root and Potted)",
      "keywordCounts": {
        "variety": 1,
        "varieties": 9,
        "genetic": 2,
        "genetics": 2,
        "patent": 1,
        "apple": 6,
        "peach": 16,
        "nectarine": 10,
        "plum": 6,
        "cherry": 4
      },
      "evidenceLinks": [
        {
          "label": "Apples",
          "url": "https://www.burchellnursery.com/apples"
        },
        {
          "label": "Nectarines",
          "url": "https://www.burchellnursery.com/nectarines"
        },
        {
          "label": "Peaches - Fresh Market",
          "url": "https://www.burchellnursery.com/peaches-fresh-market"
        },
        {
          "label": "Peaches - Processing",
          "url": "https://www.burchellnursery.com/peaches-processing"
        },
        {
          "label": "Plums",
          "url": "https://www.burchellnursery.com/plums"
        }
      ],
      "contact": {
        "url": "https://www.burchellnursery.com/contact-us/",
        "ok": true,
        "status": 200,
        "finalUrl": "https://www.burchellnursery.com/contact-us/",
        "error": "",
        "title": "Burchell Nursery Contact &mdash; Burchell Nursery",
        "checkType": "http"
      },
      "source": {
        "url": "https://www.burchellnursery.com/",
        "ok": true,
        "status": 200,
        "finalUrl": "https://www.burchellnursery.com/",
        "error": "",
        "title": "Burchell Nursery - Wholesale Tree Nursery (Bare root and Potted)",
        "checkType": "same_as_website"
      },
      "linkedin": {
        "url": "",
        "ok": false,
        "status": "",
        "finalUrl": "",
        "error": "No URL",
        "title": "",
        "checkType": "missing"
      },
      "news": [],
      "qaStatus": "verified_with_gaps",
      "auditFlags": [
        "missing_linkedin_url"
      ],
      "probedAt": "2026-07-15T19:07:10.523639+00:00"
    },
    {
      "canonicalName": "Sunview Vineyards of California",
      "website": "https://www.sunviewvineyards.com/",
      "ok": true,
      "status": 200,
      "finalUrl": "https://sunviewmarketing.com/",
      "error": "",
      "title": "Premium Table Grapes Grown in Sunny California - Sunview",
      "keywordCounts": {
        "trademark": 1,
        "brand": 4,
        "grape": 34,
        "apple": 9
      },
      "evidenceLinks": [],
      "contact": {
        "url": "https://www.sunviewvineyards.com/contact/",
        "ok": true,
        "status": 200,
        "finalUrl": "https://sunviewmarketing.com/contact/",
        "error": "",
        "title": "Contact - Sunview",
        "checkType": "http"
      },
      "source": {
        "url": "https://www.sunviewvineyards.com/",
        "ok": true,
        "status": 200,
        "finalUrl": "https://sunviewmarketing.com/",
        "error": "",
        "title": "Premium Table Grapes Grown in Sunny California - Sunview",
        "checkType": "same_as_website"
      },
      "linkedin": {
        "url": "",
        "ok": false,
        "status": "",
        "finalUrl": "",
        "error": "No URL",
        "title": "",
        "checkType": "missing"
      },
      "news": [],
      "qaStatus": "verified_with_gaps",
      "auditFlags": [
        "missing_linkedin_url"
      ],
      "probedAt": "2026-07-15T19:07:21.221532+00:00"
    },
    {
      "canonicalName": "Viveros Proseplan S.L.",
      "website": "",
      "ok": false,
      "status": "",
      "finalUrl": "",
      "error": "No URL",
      "title": "",
      "keywordCounts": {},
      "evidenceLinks": [],
      "contact": {
        "url": "",
        "ok": false,
        "status": "",
        "finalUrl": "",
        "error": "No URL",
        "title": "",
        "checkType": "missing"
      },
      "source": {
        "url": "",
        "ok": false,
        "status": "",
        "finalUrl": "",
        "error": "No URL",
        "title": "",
        "checkType": "missing"
      },
      "linkedin": {
        "url": "",
        "ok": false,
        "status": "",
        "finalUrl": "",
        "error": "No URL",
        "title": "",
        "checkType": "missing"
      },
      "news": [],
      "qaStatus": "unresolved",
      "auditFlags": [
        "missing_website",
        "missing_contact_url",
        "missing_linkedin_url",
        "missing_source_url"
      ],
      "probedAt": "2026-07-15T19:07:21.221532+00:00"
    },
    {
      "canonicalName": "ARC Infruitec-Nietvoorbij",
      "website": "https://www.arc.agric.za/arc-infruitec-nietvoorbij/Pages/ARC-InfrNietv-Homepage.aspx",
      "ok": true,
      "status": 200,
      "finalUrl": "https://www.arc.agric.za/arc-infruitec-nietvoorbij/Pages/ARC-InfrNietv-Homepage.aspx",
      "error": "",
      "title": "ARC-DECIDUOUS FRUIT, VINES AND WINE",
      "keywordCounts": {
        "cultivar": 6,
        "cultivars": 2,
        "genetic": 1,
        "brand": 1,
        "grape": 4,
        "apple": 1,
        "peach": 1,
        "nectarine": 1,
        "plum": 1
      },
      "evidenceLinks": [
        {
          "label": "",
          "url": "https://www.arc.agric.za/arc-infruitec-nietvoorbij/Pages/http&#58;//www.arc.agric.za&#58;8082/CultivarType?Category=Stone%20Fruit"
        },
        {
          "label": "",
          "url": "https://www.arc.agric.za/arc-infruitec-nietvoorbij/Pages/http&#58;//www.arc.agric.za&#58;8082/CultivarType?Category=Pome%20Fruit"
        }
      ],
      "contact": {
        "url": "https://www.arc.agric.za/arc-infruitec-nietvoorbij/Pages/Contact-Us.aspx",
        "ok": true,
        "status": 200,
        "finalUrl": "https://www.arc.agric.za/arc-infruitec-nietvoorbij/Pages/Contact-Us.aspx",
        "error": "",
        "title": "Contact Us",
        "checkType": "http"
      },
      "source": {
        "url": "https://www.arc.agric.za/arc-infruitec-nietvoorbij/Pages/ARC-InfrNietv-Homepage.aspx",
        "ok": true,
        "status": 200,
        "finalUrl": "https://www.arc.agric.za/arc-infruitec-nietvoorbij/Pages/ARC-InfrNietv-Homepage.aspx",
        "error": "",
        "title": "ARC-DECIDUOUS FRUIT, VINES AND WINE",
        "checkType": "same_as_website"
      },
      "linkedin": {
        "url": "",
        "ok": false,
        "status": "",
        "finalUrl": "",
        "error": "No URL",
        "title": "",
        "checkType": "missing"
      },
      "news": [],
      "qaStatus": "verified_with_gaps",
      "auditFlags": [
        "missing_linkedin_url"
      ],
      "probedAt": "2026-07-15T19:07:25.110822+00:00"
    },
    {
      "canonicalName": "Plant Sciences Genetics",
      "website": "https://www.plantsciencesgenetics.com/",
      "ok": true,
      "status": 200,
      "finalUrl": "https://www.plantsciencesgenetics.com/",
      "error": "",
      "title": "Plant Sciences Genetics",
      "keywordCounts": {
        "genetic": 1,
        "genetics": 1,
        "apple": 2
      },
      "evidenceLinks": [],
      "contact": {
        "url": "https://www.plantsciencesgenetics.com/contact",
        "ok": true,
        "status": 200,
        "finalUrl": "https://www.plantsciencesgenetics.com/contact",
        "error": "",
        "title": "Plant Sciences Genetics",
        "checkType": "http"
      },
      "source": {
        "url": "https://www.plantsciencesgenetics.com/",
        "ok": true,
        "status": 200,
        "finalUrl": "https://www.plantsciencesgenetics.com/",
        "error": "",
        "title": "Plant Sciences Genetics",
        "checkType": "same_as_website"
      },
      "linkedin": {
        "url": "",
        "ok": false,
        "status": "",
        "finalUrl": "",
        "error": "No URL",
        "title": "",
        "checkType": "missing"
      },
      "news": [],
      "qaStatus": "verified_with_gaps",
      "auditFlags": [
        "missing_linkedin_url"
      ],
      "probedAt": "2026-07-15T19:07:26.059411+00:00"
    },
    {
      "canonicalName": "Florida Foundation Seed Producers",
      "website": "https://ffsp.net/",
      "ok": true,
      "status": 200,
      "finalUrl": "https://ffsp.net/",
      "error": "",
      "title": "",
      "keywordCounts": {
        "varieties": 64,
        "brand": 4,
        "blueberry": 4,
        "strawberry": 4,
        "grape": 4,
        "apple": 2,
        "peach": 4,
        "nectarine": 4
      },
      "evidenceLinks": [
        {
          "label": "Varieties",
          "url": "http://ffsp.net/varieties/"
        },
        {
          "label": "Aglaonema",
          "url": "https://ffsp.net/varieties/aglaonema/"
        },
        {
          "label": "Anthurium",
          "url": "https://ffsp.net/varieties/anthurium/"
        },
        {
          "label": "Bahiagrass",
          "url": "https://ffsp.net/varieties/bahiagrass/"
        },
        {
          "label": "Basil",
          "url": "https://ffsp.net/varieties/basil/"
        },
        {
          "label": "Blueberry",
          "url": "https://ffsp.net/varieties/blueberry/"
        },
        {
          "label": "Caladium",
          "url": "https://ffsp.net/varieties/caladium/"
        },
        {
          "label": "Centipedegrass",
          "url": "https://ffsp.net/varieties/centipedegrass/"
        },
        {
          "label": "Citrus",
          "url": "https://ffsp.net/varieties/citrus/"
        },
        {
          "label": "Clover",
          "url": "https://ffsp.net/varieties/clover/"
        },
        {
          "label": "Coleus",
          "url": "https://ffsp.net/varieties/coleus/"
        },
        {
          "label": "Dieffenbachia",
          "url": "https://ffsp.net/varieties/dieffenbachia/"
        }
      ],
      "contact": {
        "url": "https://ffsp.net/contact/",
        "ok": true,
        "status": 200,
        "finalUrl": "https://ffsp.net/contact/",
        "error": "",
        "title": "Contact",
        "checkType": "http"
      },
      "source": {
        "url": "https://ffsp.net/",
        "ok": true,
        "status": 200,
        "finalUrl": "https://ffsp.net/",
        "error": "",
        "title": "",
        "checkType": "same_as_website"
      },
      "linkedin": {
        "url": "https://www.linkedin.com/company/fl-foundation-seed-producers/",
        "ok": true,
        "status": "not fetched",
        "finalUrl": "https://www.linkedin.com/company/fl-foundation-seed-producers/",
        "error": "LinkedIn blocks many automated checks; manual browser QA required.",
        "title": "",
        "checkType": "linkedin_url_format"
      },
      "news": [],
      "qaStatus": "verified_with_gaps",
      "auditFlags": [
        "linkedin_manual_check_required"
      ],
      "probedAt": "2026-07-15T19:07:26.427899+00:00"
    },
    {
      "canonicalName": "Fresh Forward",
      "website": "https://www.fresh-forward.nl/",
      "ok": true,
      "status": 200,
      "finalUrl": "https://www.fresh-forward.nl/en",
      "error": "",
      "title": "Fresh Forward | Home",
      "keywordCounts": {
        "varieties": 17,
        "brand": 1,
        "apple": 9
      },
      "evidenceLinks": [
        {
          "label": "Our varieties",
          "url": "https://www.fresh-forward.nl/en/our-varieties/B"
        },
        {
          "label": "Apples",
          "url": "https://www.fresh-forward.nl/en/our-varieties/apples"
        }
      ],
      "contact": {
        "url": "https://www.fresh-forward.nl/en/contact",
        "ok": true,
        "status": 200,
        "finalUrl": "https://www.fresh-forward.nl/en/contact",
        "error": "",
        "title": "Fresh Forward | Contact",
        "checkType": "http"
      },
      "source": {
        "url": "https://www.fresh-forward.nl/",
        "ok": true,
        "status": 200,
        "finalUrl": "https://www.fresh-forward.nl/en",
        "error": "",
        "title": "Fresh Forward | Home",
        "checkType": "same_as_website"
      },
      "linkedin": {
        "url": "https://www.linkedin.com/company/fresh-forward/",
        "ok": true,
        "status": "not fetched",
        "finalUrl": "https://www.linkedin.com/company/fresh-forward/",
        "error": "LinkedIn blocks many automated checks; manual browser QA required.",
        "title": "",
        "checkType": "linkedin_url_format"
      },
      "news": [],
      "qaStatus": "verified_with_gaps",
      "auditFlags": [
        "linkedin_manual_check_required"
      ],
      "probedAt": "2026-07-15T19:07:28.643711+00:00"
    },
    {
      "canonicalName": "Prevar",
      "website": "https://www.prevar.co.nz/",
      "ok": true,
      "status": 200,
      "finalUrl": "https://www.prevar.co.nz/",
      "error": "",
      "title": "Prevar &#8211; The future of fruit innovation",
      "keywordCounts": {
        "varieties": 1,
        "cultivar": 1,
        "cultivars": 1,
        "brand": 66,
        "apple": 3
      },
      "evidenceLinks": [
        {
          "label": "Brands",
          "url": "https://www.prevar.co.nz/brands/"
        },
        {
          "label": "Rockit™",
          "url": "https://www.prevar.co.nz/index.php/brands/#rockit"
        },
        {
          "label": "PIQA®",
          "url": "https://www.prevar.co.nz/index.php/brands/#piqaboo"
        },
        {
          "label": "Dazzle™",
          "url": "https://www.prevar.co.nz/index.php/brands/#dazzle"
        },
        {
          "label": "GoodnessMe®",
          "url": "https://www.prevar.co.nz/brands/#goodness-me"
        },
        {
          "label": "Sassy™",
          "url": "https://www.prevar.co.nz/index.php/brands/#sassy"
        },
        {
          "label": "Lemonade™",
          "url": "https://www.prevar.co.nz/index.php/brands/#lemonade"
        },
        {
          "label": "Cherish™",
          "url": "https://www.prevar.co.nz/index.php/brands/#cherish"
        },
        {
          "label": "Smitten®",
          "url": "https://www.prevar.co.nz/index.php/brands/#smitten"
        },
        {
          "label": "Posh™",
          "url": "https://www.prevar.co.nz/index.php/brands/#posh"
        },
        {
          "label": "Joli™",
          "url": "https://www.prevar.co.nz/index.php/brands/#joli"
        },
        {
          "label": "FIZZ™",
          "url": "https://www.prevar.co.nz/brands/#fizz"
        }
      ],
      "contact": {
        "url": "https://www.prevar.co.nz/contact/",
        "ok": true,
        "status": 200,
        "finalUrl": "https://www.prevar.co.nz/contact/",
        "error": "",
        "title": "Contact &#8211; Prevar",
        "checkType": "http"
      },
      "source": {
        "url": "https://www.prevar.co.nz/",
        "ok": true,
        "status": 200,
        "finalUrl": "https://www.prevar.co.nz/",
        "error": "",
        "title": "Prevar &#8211; The future of fruit innovation",
        "checkType": "same_as_website"
      },
      "linkedin": {
        "url": "https://www.linkedin.com/company/prevar-limited/",
        "ok": true,
        "status": "not fetched",
        "finalUrl": "https://www.linkedin.com/company/prevar-limited/",
        "error": "LinkedIn blocks many automated checks; manual browser QA required.",
        "title": "",
        "checkType": "linkedin_url_format"
      },
      "news": [],
      "qaStatus": "verified_with_gaps",
      "auditFlags": [
        "linkedin_manual_check_required"
      ],
      "probedAt": "2026-07-15T19:07:30.627594+00:00"
    },
    {
      "canonicalName": "Planasa",
      "website": "https://planasa.com/",
      "ok": true,
      "status": 200,
      "finalUrl": "https://planasa.com/",
      "error": "",
      "title": "HOME - Planasa",
      "keywordCounts": {
        "variety": 2,
        "varieties": 17,
        "genetic": 3,
        "genetics": 3,
        "brand": 5,
        "blueberry": 10,
        "strawberry": 5,
        "raspberry": 10,
        "blackberry": 9,
        "apple": 1
      },
      "evidenceLinks": [
        {
          "label": "Varieties",
          "url": "https://planasa.com/varieties/"
        },
        {
          "label": "",
          "url": "https://planasa.com/product/blueberry/"
        },
        {
          "label": "",
          "url": "https://planasa.com/product/blackberry/"
        },
        {
          "label": "",
          "url": "https://planasa.com/product/strawberry/"
        },
        {
          "label": "",
          "url": "https://planasa.com/product/raspberry/"
        },
        {
          "label": "Blueberry",
          "url": "https://planasa.com/blueberry/"
        },
        {
          "label": "Raspberry",
          "url": "https://planasa.com/raspberry/"
        },
        {
          "label": "Strawberry",
          "url": "https://planasa.com/strawberry/"
        }
      ],
      "contact": {
        "url": "https://planasa.com/contact/",
        "ok": true,
        "status": 200,
        "finalUrl": "https://planasa.com/contact/",
        "error": "",
        "title": "CONTACT - Planasa",
        "checkType": "http"
      },
      "source": {
        "url": "https://planasa.com/",
        "ok": true,
        "status": 200,
        "finalUrl": "https://planasa.com/",
        "error": "",
        "title": "HOME - Planasa",
        "checkType": "same_as_website"
      },
      "linkedin": {
        "url": "https://www.linkedin.com/company/planasa/",
        "ok": true,
        "status": "not fetched",
        "finalUrl": "https://www.linkedin.com/company/planasa/",
        "error": "LinkedIn blocks many automated checks; manual browser QA required.",
        "title": "",
        "checkType": "linkedin_url_format"
      },
      "news": [],
      "qaStatus": "verified_with_gaps",
      "auditFlags": [
        "linkedin_manual_check_required"
      ],
      "probedAt": "2026-07-15T19:07:32.601435+00:00"
    },
    {
      "canonicalName": "Costa Berry International",
      "website": "https://costagroup.com.au/",
      "ok": true,
      "status": 200,
      "finalUrl": "https://costagroup.com.au/",
      "error": "",
      "title": "Home - Costa Group",
      "keywordCounts": {
        "varieties": 4,
        "brand": 20,
        "blueberry": 1,
        "blackberry": 1,
        "grape": 27,
        "apple": 2
      },
      "evidenceLinks": [
        {
          "label": "Brand Pillars",
          "url": "https://costagroup.com.au/about-us/#brand-pillars"
        },
        {
          "label": "Grapes",
          "url": "https://costagroup.com.au/produce/#grapes_section"
        },
        {
          "label": "BluGenix powers the future of blueberries &nbsp; Costa Group has celebrated a significant milestone in the development o",
          "url": "https://costagroup.com.au/2026/05/29/blugenix-powers-the-future-of-blueberries/"
        },
        {
          "label": "Crisp, fresh, flavour-packed grapes in every bite",
          "url": "https://www.instagram.com/p/DZWT-FhzytB/"
        }
      ],
      "contact": {
        "url": "https://costagroup.com.au/contact-us/",
        "ok": true,
        "status": 200,
        "finalUrl": "https://costagroup.com.au/contact-us/",
        "error": "",
        "title": "Contact - Costa Group",
        "checkType": "http"
      },
      "source": {
        "url": "https://costagroup.com.au/",
        "ok": true,
        "status": 200,
        "finalUrl": "https://costagroup.com.au/",
        "error": "",
        "title": "Home - Costa Group",
        "checkType": "same_as_website"
      },
      "linkedin": {
        "url": "https://www.linkedin.com/company/costagroup/",
        "ok": true,
        "status": "not fetched",
        "finalUrl": "https://www.linkedin.com/company/costagroup/",
        "error": "LinkedIn blocks many automated checks; manual browser QA required.",
        "title": "",
        "checkType": "linkedin_url_format"
      },
      "news": [],
      "qaStatus": "verified_with_gaps",
      "auditFlags": [
        "linkedin_manual_check_required"
      ],
      "probedAt": "2026-07-15T19:07:35.876653+00:00"
    },
    {
      "canonicalName": "Mountain Blue Orchards Pty Ltd",
      "website": "https://mountainblue.com.au/",
      "ok": true,
      "status": 200,
      "finalUrl": "https://www.mountainblue.com.au/",
      "error": "",
      "title": "Mountain Blue",
      "keywordCounts": {
        "genetic": 24,
        "genetics": 24,
        "brand": 7,
        "blueberry": 4
      },
      "evidenceLinks": [
        {
          "label": "Genetics",
          "url": "https://www.mountainblue.com.au/mountain-blue-genetics"
        },
        {
          "label": "",
          "url": "https://www.mountainblue.com.au/brands"
        },
        {
          "label": "Brands",
          "url": "https://www.mountainblue.com.au/eureka-blueberries"
        }
      ],
      "contact": {
        "url": "https://www.mountainblue.com.au/contact-us/",
        "ok": true,
        "status": 200,
        "finalUrl": "https://www.mountainblue.com.au/contact-us/",
        "error": "",
        "title": "Contact Us &mdash; Mountain Blue",
        "checkType": "http"
      },
      "source": {
        "url": "https://mountainblue.com.au/",
        "ok": true,
        "status": 200,
        "finalUrl": "https://www.mountainblue.com.au/",
        "error": "",
        "title": "Mountain Blue",
        "checkType": "same_as_website"
      },
      "linkedin": {
        "url": "https://www.linkedin.com/company/mountain-blue/",
        "ok": true,
        "status": "not fetched",
        "finalUrl": "https://www.linkedin.com/company/mountain-blue/",
        "error": "LinkedIn blocks many automated checks; manual browser QA required.",
        "title": "",
        "checkType": "linkedin_url_format"
      },
      "news": [],
      "qaStatus": "verified_with_gaps",
      "auditFlags": [
        "linkedin_manual_check_required"
      ],
      "probedAt": "2026-07-15T19:07:36.662083+00:00"
    },
    {
      "canonicalName": "CIV - Consorzio Italiano Vivaisti",
      "website": "https://civ.it/en/",
      "ok": true,
      "status": 200,
      "finalUrl": "https://civ.it/en/",
      "error": "",
      "title": "Home - CIV - Consorzio Italiano Vivaisti",
      "keywordCounts": {
        "variety": 2,
        "varieties": 13,
        "genetic": 1,
        "apple": 13
      },
      "evidenceLinks": [
        {
          "label": "Apples",
          "url": "https://civ.it/en/apples/"
        }
      ],
      "contact": {
        "url": "https://civ.it/en/contact-us/",
        "ok": true,
        "status": 200,
        "finalUrl": "https://civ.it/en/contact-us/",
        "error": "",
        "title": "Contact us - CIV - Consorzio Italiano Vivaisti",
        "checkType": "http"
      },
      "source": {
        "url": "https://civ.it/en/",
        "ok": true,
        "status": 200,
        "finalUrl": "https://civ.it/en/",
        "error": "",
        "title": "Home - CIV - Consorzio Italiano Vivaisti",
        "checkType": "same_as_website"
      },
      "linkedin": {
        "url": "",
        "ok": false,
        "status": "",
        "finalUrl": "",
        "error": "No URL",
        "title": "",
        "checkType": "missing"
      },
      "news": [],
      "qaStatus": "verified_with_gaps",
      "auditFlags": [
        "missing_linkedin_url"
      ],
      "probedAt": "2026-07-15T19:07:38.193341+00:00"
    },
    {
      "canonicalName": "USDA Agricultural Research Service",
      "website": "https://www.ars.usda.gov/",
      "ok": true,
      "status": 200,
      "finalUrl": "https://www.ars.usda.gov/",
      "error": "",
      "title": "ARS Home : USDA ARS",
      "keywordCounts": {
        "varieties": 7,
        "brand": 2,
        "apple": 2
      },
      "evidenceLinks": [
        {
          "label": "here",
          "url": "https://scientificdiscoveries.ars.usda.gov/explore-our-discoveries/ars-discovery-within-popular-cover-crop-spurs-development-new-varieties"
        }
      ],
      "contact": {
        "url": "https://www.ars.usda.gov/oc/",
        "ok": true,
        "status": 200,
        "finalUrl": "https://www.ars.usda.gov/oc/",
        "error": "",
        "title": "Office of Communications : USDA ARS",
        "checkType": "http"
      },
      "source": {
        "url": "https://www.ars.usda.gov/",
        "ok": true,
        "status": 200,
        "finalUrl": "https://www.ars.usda.gov/",
        "error": "",
        "title": "ARS Home : USDA ARS",
        "checkType": "same_as_website"
      },
      "linkedin": {
        "url": "https://www.linkedin.com/company/usda-ars/",
        "ok": true,
        "status": "not fetched",
        "finalUrl": "https://www.linkedin.com/company/usda-ars/",
        "error": "LinkedIn blocks many automated checks; manual browser QA required.",
        "title": "",
        "checkType": "linkedin_url_format"
      },
      "news": [],
      "qaStatus": "verified_with_gaps",
      "auditFlags": [
        "linkedin_manual_check_required"
      ],
      "probedAt": "2026-07-15T19:07:38.742961+00:00"
    },
    {
      "canonicalName": "Agriculture and Agri-Food Canada",
      "website": "https://agriculture.canada.ca/",
      "ok": true,
      "status": 200,
      "finalUrl": "https://agriculture.canada.ca/",
      "error": "",
      "title": "Language selection - Agriculture and Agri-Food Canada / Sélection de la langue - Agriculture et Agroalimentaire Canada",
      "keywordCounts": {
        "apple": 1
      },
      "evidenceLinks": [],
      "contact": {
        "url": "https://agriculture.canada.ca/en/contact-agriculture-and-agri-food-canada",
        "ok": true,
        "status": 200,
        "finalUrl": "https://agriculture.canada.ca/en/contact",
        "error": "",
        "title": "Contact Agriculture and Agri-Food Canada - agriculture.canada.ca",
        "checkType": "http"
      },
      "source": {
        "url": "https://agriculture.canada.ca/",
        "ok": true,
        "status": 200,
        "finalUrl": "https://agriculture.canada.ca/",
        "error": "",
        "title": "Language selection - Agriculture and Agri-Food Canada / Sélection de la langue - Agriculture et Agroalimentaire Canada",
        "checkType": "same_as_website"
      },
      "linkedin": {
        "url": "",
        "ok": false,
        "status": "",
        "finalUrl": "",
        "error": "No URL",
        "title": "",
        "checkType": "missing"
      },
      "news": [],
      "qaStatus": "verified_with_gaps",
      "auditFlags": [
        "missing_linkedin_url"
      ],
      "probedAt": "2026-07-15T19:07:39.476162+00:00"
    },
    {
      "canonicalName": "University of Florida",
      "website": "https://ifas.ufl.edu/",
      "ok": true,
      "status": 200,
      "finalUrl": "https://ifas.ufl.edu/",
      "error": "",
      "title": "University of Florida Institute of Food and Agricultural Sciences - University of Florida, Institute of Food and Agricultural Sciences - UF/IFAS",
      "keywordCounts": {
        "variety": 5,
        "brand": 5
      },
      "evidenceLinks": [
        {
          "label": "Question: I think I have a new variety of plant and want to name it. What do I do?",
          "url": "https://blogs.ifas.ufl.edu/news/2026/07/13/question-i-think-i-have-a-new-variety-of-plant-and-want-to-name-it-what-do-i-do/"
        }
      ],
      "contact": {
        "url": "",
        "ok": false,
        "status": "",
        "finalUrl": "",
        "error": "No URL",
        "title": "",
        "checkType": "missing"
      },
      "source": {
        "url": "https://ifas.ufl.edu/",
        "ok": true,
        "status": 200,
        "finalUrl": "https://ifas.ufl.edu/",
        "error": "",
        "title": "University of Florida Institute of Food and Agricultural Sciences - University of Florida, Institute of Food and Agricultural Sciences - UF/IFAS",
        "checkType": "same_as_website"
      },
      "linkedin": {
        "url": "https://www.linkedin.com/school/ufifas/",
        "ok": true,
        "status": "not fetched",
        "finalUrl": "https://www.linkedin.com/school/ufifas/",
        "error": "LinkedIn blocks many automated checks; manual browser QA required.",
        "title": "",
        "checkType": "linkedin_url_format"
      },
      "news": [
        {
          "url": "https://news.ifas.ufl.edu/",
          "ok": true,
          "status": 200,
          "finalUrl": "https://blogs.ifas.ufl.edu/news/",
          "error": "",
          "title": "News -",
          "checkType": "http",
          "label": "UF/IFAS news"
        }
      ],
      "qaStatus": "verified_with_gaps",
      "auditFlags": [
        "missing_contact_url",
        "linkedin_manual_check_required"
      ],
      "probedAt": "2026-07-15T19:07:40.483885+00:00"
    },
    {
      "canonicalName": "INRAE",
      "website": "https://www.inrae.fr/en",
      "ok": true,
      "status": 200,
      "finalUrl": "https://www.inrae.fr/en",
      "error": "",
      "title": "INRAE: research for Agriculture, Food and Environment",
      "keywordCounts": {
        "genetic": 2,
        "genetics": 2,
        "apple": 3
      },
      "evidenceLinks": [
        {
          "label": "Nicolas Rode, researcher in evolutionary genetics research scientist",
          "url": "https://www.inrae.fr/en/news/nicolas-rode-researcher-evolutionary-genetics"
        }
      ],
      "contact": {
        "url": "https://www.inrae.fr/en/contact",
        "ok": true,
        "status": 200,
        "finalUrl": "https://www.inrae.fr/en/contact",
        "error": "",
        "title": "Contact us|INRAE",
        "checkType": "http"
      },
      "source": {
        "url": "https://www.inrae.fr/en",
        "ok": true,
        "status": 200,
        "finalUrl": "https://www.inrae.fr/en",
        "error": "",
        "title": "INRAE: research for Agriculture, Food and Environment",
        "checkType": "same_as_website"
      },
      "linkedin": {
        "url": "",
        "ok": false,
        "status": "",
        "finalUrl": "",
        "error": "No URL",
        "title": "",
        "checkType": "missing"
      },
      "news": [
        {
          "url": "https://www.inrae.fr/en/news-brief",
          "ok": true,
          "status": 200,
          "finalUrl": "https://www.inrae.fr/en/news-brief",
          "error": "",
          "title": "News brief | INRAE",
          "checkType": "http",
          "label": "INRAE news briefs"
        },
        {
          "url": "https://www.inrae.fr/en/press",
          "ok": true,
          "status": 200,
          "finalUrl": "https://www.inrae.fr/en/press",
          "error": "",
          "title": "Press room | INRAE",
          "checkType": "http",
          "label": "INRAE press"
        }
      ],
      "qaStatus": "verified_with_gaps",
      "auditFlags": [
        "missing_linkedin_url"
      ],
      "probedAt": "2026-07-15T19:07:42.767738+00:00"
    },
    {
      "canonicalName": "Plant & Food Research",
      "website": "https://www.plantandfood.com/en-nz",
      "ok": true,
      "status": 200,
      "finalUrl": "https://www.plantandfood.com/en-nz",
      "error": "",
      "title": "A smart green future. Together. · Plant &amp; Food Research",
      "keywordCounts": {
        "variety": 4,
        "varieties": 25,
        "cultivar": 4,
        "cultivars": 3,
        "genetic": 14,
        "genetics": 3,
        "apple": 26,
        "peach": 9
      },
      "evidenceLinks": [
        {
          "label": "New plant cultivars",
          "url": "https://www.plantandfood.com/en-nz/new-plant-cultivars"
        },
        {
          "label": "Genetics &amp; genomics",
          "url": "https://www.plantandfood.com/en-nz/genetics-and-genomics"
        },
        {
          "label": "Plant varieties",
          "url": "https://www.plantandfood.com/en-nz/plant-varieties"
        },
        {
          "label": "Grow our varieties at home",
          "url": "https://www.plantandfood.com/en-nz/grow-our-varieties-at-home"
        },
        {
          "label": "Extend your portfolio",
          "url": "https://www.plantandfood.com/en-nz/license-a-new-cultivar"
        },
        {
          "label": "On genetic modification",
          "url": "https://www.plantandfood.com/en-nz/our-views-on-genetic-modification"
        },
        {
          "label": "",
          "url": "https://www.plantandfood.com/en-nz/article/next-generation-nz-hop-variety-launched-for-brewing-industry"
        },
        {
          "label": "",
          "url": "https://www.plantandfood.com/en-nz/article/the-arctic-apple-story"
        }
      ],
      "contact": {
        "url": "https://www.plantandfood.com/en-nz/contact-us",
        "ok": true,
        "status": 200,
        "finalUrl": "https://www.plantandfood.com/en-nz/contact-us",
        "error": "",
        "title": "Contact us · Plant &amp; Food Research",
        "checkType": "http"
      },
      "source": {
        "url": "https://www.plantandfood.com/en-nz",
        "ok": true,
        "status": 200,
        "finalUrl": "https://www.plantandfood.com/en-nz",
        "error": "",
        "title": "A smart green future. Together. · Plant &amp; Food Research",
        "checkType": "same_as_website"
      },
      "linkedin": {
        "url": "",
        "ok": false,
        "status": "",
        "finalUrl": "",
        "error": "No URL",
        "title": "",
        "checkType": "missing"
      },
      "news": [],
      "qaStatus": "verified_with_gaps",
      "auditFlags": [
        "missing_linkedin_url"
      ],
      "probedAt": "2026-07-15T19:07:43.213284+00:00"
    },
    {
      "canonicalName": "University of California",
      "website": "https://itc.ucdavis.edu/",
      "ok": true,
      "status": 200,
      "finalUrl": "https://research.ucdavis.edu/",
      "error": "",
      "title": "Home - Office of Research",
      "keywordCounts": {
        "variety": 2,
        "patent": 1,
        "brand": 1,
        "raspberry": 7
      },
      "evidenceLinks": [
        {
          "label": "Plant Variety Licensing Program",
          "url": "https://research.ucdavis.edu/industry-support/plant-variety-licensing-program/"
        }
      ],
      "contact": {
        "url": "https://itc.ucdavis.edu/contact",
        "ok": true,
        "status": 200,
        "finalUrl": "https://research.ucdavis.edu/",
        "error": "",
        "title": "Home - Office of Research",
        "checkType": "http"
      },
      "source": {
        "url": "https://itc.ucdavis.edu/",
        "ok": true,
        "status": 200,
        "finalUrl": "https://research.ucdavis.edu/",
        "error": "",
        "title": "Home - Office of Research",
        "checkType": "same_as_website"
      },
      "linkedin": {
        "url": "https://www.linkedin.com/school/uc-davis/",
        "ok": true,
        "status": "not fetched",
        "finalUrl": "https://www.linkedin.com/school/uc-davis/",
        "error": "LinkedIn blocks many automated checks; manual browser QA required.",
        "title": "",
        "checkType": "linkedin_url_format"
      },
      "news": [
        {
          "url": "https://itc.ucdavis.edu/news",
          "ok": true,
          "status": 200,
          "finalUrl": "https://research.ucdavis.edu/",
          "error": "",
          "title": "Home - Office of Research",
          "checkType": "http",
          "label": "UC Davis innovation news"
        }
      ],
      "qaStatus": "verified_with_gaps",
      "auditFlags": [
        "linkedin_manual_check_required"
      ],
      "probedAt": "2026-07-15T19:07:46.659176+00:00"
    },
    {
      "canonicalName": "University of Arkansas System Division of Agriculture",
      "website": "https://aaes.uada.edu/research/horticulture/fruit-breeding/",
      "ok": true,
      "status": 200,
      "finalUrl": "https://aaes.uada.edu/fruit-breeding/",
      "error": "",
      "title": "Fruit Breeding",
      "keywordCounts": {
        "variety": 6,
        "cultivar": 3,
        "cultivars": 3,
        "genetic": 6,
        "genetics": 4,
        "blackberry": 6,
        "grape": 17,
        "apple": 15,
        "peach": 10,
        "nectarine": 4
      },
      "evidenceLinks": [
        {
          "label": "Variety Testing",
          "url": "https://aaes.uada.edu/variety-testing/"
        },
        {
          "label": "genetic location of primocane-fruiting",
          "url": "https://aaes.uada.edu/news/primocane-blackberry-genetics/"
        },
        {
          "label": "thornlessness",
          "url": "https://aaes.uada.edu/news/genetic-region-blackberry-thorns/"
        },
        {
          "label": "crossbreed muscadines and Vitis vinifera grapes",
          "url": "https://aaes.uada.edu/news/vitis-to-muscadinia/"
        },
        {
          "label": "LEARN MORE",
          "url": "https://aaes.uada.edu/fruit-breeding/grapes/"
        },
        {
          "label": "LEARN MORE",
          "url": "https://aaes.uada.edu/fruit-breeding/peaches-and-nectarines/"
        }
      ],
      "contact": {
        "url": "",
        "ok": false,
        "status": "",
        "finalUrl": "",
        "error": "No URL",
        "title": "",
        "checkType": "missing"
      },
      "source": {
        "url": "https://aaes.uada.edu/research/horticulture/fruit-breeding/",
        "ok": true,
        "status": 200,
        "finalUrl": "https://aaes.uada.edu/fruit-breeding/",
        "error": "",
        "title": "Fruit Breeding",
        "checkType": "same_as_website"
      },
      "linkedin": {
        "url": "https://www.linkedin.com/school/university-of-arkansas/",
        "ok": true,
        "status": "not fetched",
        "finalUrl": "https://www.linkedin.com/school/university-of-arkansas/",
        "error": "LinkedIn blocks many automated checks; manual browser QA required.",
        "title": "",
        "checkType": "linkedin_url_format"
      },
      "news": [
        {
          "url": "https://www.uaex.uada.edu/media-resources/news/",
          "ok": true,
          "status": 200,
          "finalUrl": "https://www.uaex.uada.edu/media-resources/news/",
          "error": "",
          "title": "News from the U of A Division of Agriculture Cooperative Extension Service | Facts about Arkansas ag",
          "checkType": "http",
          "label": "Arkansas Ag news"
        }
      ],
      "qaStatus": "verified_with_gaps",
      "auditFlags": [
        "missing_contact_url",
        "linkedin_manual_check_required"
      ],
      "probedAt": "2026-07-15T19:07:48.341709+00:00"
    }
  ]
}
